redleg/__init__.py
redleg/__main__.py
redleg-1.0.0.dist-info/METADATA
redleg-1.0.0.dist-info/WHEEL
redleg-1.0.0.dist-info/entry_points.txt
redleg-1.0.0.dist-info/licenses/LICENSE
redleg-1.0.0.dist-info/RECORD
