Metadata-Version: 2.4
Name: RedLeg
Version: 1.0.0
Summary: A simple dual entry ledger application
Project-URL: homepage, https://github.com/TheCrunching/RedLeg
Project-URL: source, https://github.com/TheCrunching/RedLeg/
Project-URL: download, https://github.com/TheCrunching/redleg/releases/tag/v0.1.2
Project-URL: changelog, https://github.com/TheCrunching/RedLeg/blob/main/CHANGELOG.md
Project-URL: releasenotes, https://github.com/TheCrunching/redleg/releases/tag/v1.0.0-beta1
Project-URL: documentation, https://github.com/TheCrunching/RedLeg/blob/main/README.md
Project-URL: issues, https://github.com/TheCrunching/RedLeg/issues
Author-email: TheCrunching <theCrunching@proton.me>
Maintainer-email: TheCrunching <theCrunching@proton.me>
License-Expression: MIT
License-File: LICENSE
Keywords: accounting,ledger,money
Classifier: Development Status :: 5 - Production/Stable
Classifier: Environment :: Console
Classifier: Framework :: Hatch
Classifier: License :: OSI Approved :: MIT License
Classifier: Natural Language :: English
Classifier: Operating System :: OS Independent
Classifier: Programming Language :: Python
Classifier: Programming Language :: Python :: 3
Classifier: Programming Language :: Python :: 3 :: Only
Classifier: Topic :: File Formats :: JSON
Classifier: Topic :: File Formats :: JSON :: JSON Schema
Classifier: Topic :: Office/Business
Classifier: Topic :: Office/Business :: Financial
Classifier: Topic :: Office/Business :: Financial :: Accounting
Classifier: Typing :: Typed
Requires-Python: >=3.9
